EigenLedger/__init__.py
EigenLedger/main.py
EigenLedger/modules/empyrical/.gitattributes
EigenLedger/modules/empyrical/.gitignore
EigenLedger/modules/empyrical/.travis.yml
EigenLedger/modules/empyrical/__init__.py
EigenLedger/modules/empyrical/_version.py
EigenLedger/modules/empyrical/deprecate.py
EigenLedger/modules/empyrical/perf_attrib.py
EigenLedger/modules/empyrical/periods.py
EigenLedger/modules/empyrical/stats.py
EigenLedger/modules/empyrical/utils.py
eigenledger-2.1.6.dist-info/LICENSE
eigenledger-2.1.6.dist-info/METADATA
eigenledger-2.1.6.dist-info/WHEEL
eigenledger-2.1.6.dist-info/RECORD
