Metadata-Version: 2.1
Name: EigenLedger
Version: 2.1.6
Summary: An Open Source Portfolio Management Framework for Everyone 投资组合管理
Home-page: https://github.com/ssantoshp/EigenLedger
License: LICENSE
Author: Santosh
Author-email: santoshpassoubadyp@gmail.com
Requires-Python: >=3.0
Classifier: License :: Other/Proprietary License
Classifier: Programming Language :: Python :: 3
Classifier: Programming Language :: Python :: 3.4
Classifier: Programming Language :: Python :: 3.5
Classifier: Programming Language :: Python :: 3.6
Classifier: Programming Language :: Python :: 3.7
Classifier: Programming Language :: Python :: 3.8
Classifier: Programming Language :: Python :: 3.9
Classifier: Programming Language :: Python :: 3.10
Classifier: Programming Language :: Python :: 3.11
Classifier: Programming Language :: Python :: 3.12
Classifier: Programming Language :: Python :: 3.13
Requires-Dist: fpdf (>=1.7.2,<2.0.0)
Requires-Dist: ipython (>=7.16.0,<8.0.0)
Requires-Dist: matplotlib (>=3.4.0,<4.0.0)
Requires-Dist: numpy (>=1.21.0,<2.0.0)
Requires-Dist: pyportfolioopt (>=1.4.0,<2.0.0)
Requires-Dist: quantstats (>=0.0.62,<0.0.63)
Requires-Dist: yfinance (>=0.1.0,<0.2.0)
